payments_py/__init__.py
payments_py/a2a/__init__.py
payments_py/a2a/agent_card.py
payments_py/a2a/client_registry.py
payments_py/a2a/payments_client.py
payments_py/a2a/payments_request_handler.py
payments_py/a2a/server.py
payments_py/a2a/types.py
payments_py/api/__init__.py
payments_py/api/agents_api.py
payments_py/api/base_payments.py
payments_py/api/contracts_api.py
payments_py/api/nvm_api.py
payments_py/api/observability_api.py
payments_py/api/plans_api.py
payments_py/api/query_api.py
payments_py/api/requests_api.py
payments_py/common/__init__.py
payments_py/common/data_models.py
payments_py/common/helper.py
payments_py/common/payments_error.py
payments_py/common/types.py
payments_py/environments.py
payments_py/mcp/__init__.py
payments_py/mcp/core/auth.py
payments_py/mcp/core/credits_context.py
payments_py/mcp/core/paywall.py
payments_py/mcp/core/server_manager.py
payments_py/mcp/http/__init__.py
payments_py/mcp/http/client_registration.py
payments_py/mcp/http/mcp_handler.py
payments_py/mcp/http/oauth_metadata.py
payments_py/mcp/http/oauth_router.py
payments_py/mcp/http/session_manager.py
payments_py/mcp/index.py
payments_py/mcp/payments_mcp.py
payments_py/mcp/types/__init__.py
payments_py/mcp/types/http_types.py
payments_py/mcp/types/paywall_types.py
payments_py/mcp/types/server_types.py
payments_py/mcp/utils/errors.py
payments_py/mcp/utils/extra.py
payments_py/mcp/utils/logical_url.py
payments_py/mcp/utils/request.py
payments_py/payments.py
payments_py/plans.py
payments_py/utils.py
payments_py/x402/README.md
payments_py/x402/__init__.py
payments_py/x402/a2a.py
payments_py/x402/extensions/__init__.py
payments_py/x402/extensions/nevermined/README.md
payments_py/x402/extensions/nevermined/__init__.py
payments_py/x402/extensions/nevermined/declare.py
payments_py/x402/extensions/nevermined/extract.py
payments_py/x402/extensions/nevermined/types.py
payments_py/x402/extensions/nevermined/validate.py
payments_py/x402/facilitator.py
payments_py/x402/facilitator_api.py
payments_py-1.0.3.dist-info/METADATA
payments_py-1.0.3.dist-info/WHEEL
payments_py-1.0.3.dist-info/licenses/LICENSE
payments_py-1.0.3.dist-info/RECORD
