Metadata-Version: 2.4
Name: payments-py
Version: 1.0.3
Summary: 
License-File: LICENSE
Author: enrique
Author-email: enrique@nevermined.io
Requires-Python: >=3.10,<4.0
Classifier: Programming Language :: Python :: 3
Classifier: Programming Language :: Python :: 3.10
Classifier: Programming Language :: Python :: 3.11
Classifier: Programming Language :: Python :: 3.12
Classifier: Programming Language :: Python :: 3.13
Classifier: Programming Language :: Python :: 3.14
Provides-Extra: fastapi
Requires-Dist: a2a-sdk (>=0.3.0,<0.4.0)
Requires-Dist: aiohttp (>=3.10.8,<4.0.0)
Requires-Dist: black (>=26.1.0,<27.0.0)
Requires-Dist: fastapi (>=0.120.0,<0.121.0) ; extra == "fastapi"
Requires-Dist: helicone-helpers (>=1.1.1,<2.0.0)
Requires-Dist: jsonschema (>=4.25.1,<5.0.0)
Requires-Dist: mcp (>=1.25.0,<2.0.0)
Requires-Dist: mike (>=2.1.0,<3.0.0)
Requires-Dist: mkdocs (>=1.5.3,<2.0.0)
Requires-Dist: mkdocs-material (>=9.5.0,<10.0.0)
Requires-Dist: mkdocstrings[python] (>=0.29.0,<0.30.0)
Requires-Dist: pydantic (>=2.8.2,<3.0.0)
Requires-Dist: pyjwt (>=2.9.0,<3.0.0)
Requires-Dist: pytest-asyncio (>=1.2.0,<2.0.0)
Requires-Dist: python-socketio (==5.14.3)
Requires-Dist: requests (>=2.31.0,<3.0.0)
Requires-Dist: starlette (>=0.49.1,<0.50.0) ; extra == "fastapi"
Requires-Dist: websocket-client (>=1.8.0,<2.0.0)
